kltpicker/ASOCEM_one_sample.py
kltpicker/__init__.py
kltpicker/__main__.py
kltpicker/cryo_utils.py
kltpicker/kltpicker.py
kltpicker/kltpicker_input.py
kltpicker/main.py
kltpicker/micrograph.py
kltpicker/util.py
kltpicker2-2.0.1.dist-info/LICENSE
kltpicker2-2.0.1.dist-info/METADATA
kltpicker2-2.0.1.dist-info/WHEEL
kltpicker2-2.0.1.dist-info/entry_points.txt
kltpicker2-2.0.1.dist-info/top_level.txt
kltpicker2-2.0.1.dist-info/RECORD
