Metadata-Version: 2.1
Name: kltpicker2
Version: 2.0.1
Summary: KLT Picker: Particle picking using data-driven optimal templates
Home-page: https://github.com/ShkolniskyLab/kltpicker2
Author: Yoel Shkolnisky
Author-email: yoelsh@tauex.tau.ac.il
License: GNU General Public License v3.0
Platform: UNKNOWN
Requires-Python: ~=3.6
License-File: LICENSE
Requires-Dist: numpy (>=1.16)
Requires-Dist: mrcfile
Requires-Dist: scipy (>=1.3)
Requires-Dist: pyfftw
Requires-Dist: progressbar2
Requires-Dist: numba
Requires-Dist: scikit-image
Requires-Dist: opencv-python
Provides-Extra: gpu
Requires-Dist: cupy ; extra == 'gpu'
